sec_pass_manager-1.3.0.dist-info/licenses/LICENSE
spm/__init__.py
spm/console_interface.py
spm/sec_pass_manager.py
sec_pass_manager-1.3.0.dist-info/METADATA
sec_pass_manager-1.3.0.dist-info/WHEEL
sec_pass_manager-1.3.0.dist-info/entry_points.txt
sec_pass_manager-1.3.0.dist-info/top_level.txt
sec_pass_manager-1.3.0.dist-info/RECORD
