Metadata-Version: 2.4
Name: sec-pass-manager
Version: 1.3.0
Summary: A secure password manager that creates random passwords and saves them as encrypted files
Author-email: santipvz <santivzqzz@gmail.com>
License: MIT
Project-URL: Homepage, https://github.com/santipvz/SecurePasswordManager
Project-URL: Repository, https://github.com/santipvz/SecurePasswordManager
Project-URL: Issues, https://github.com/santipvz/SecurePasswordManager/issues
Keywords: password,manager,security,generator,cli
Classifier: Development Status :: 4 - Beta
Classifier: Intended Audience :: End Users/Desktop
Classifier: Operating System :: OS Independent
Classifier: Programming Language :: Python :: 3
Classifier: Programming Language :: Python :: 3.7
Classifier: Programming Language :: Python :: 3.8
Classifier: Programming Language :: Python :: 3.9
Classifier: Programming Language :: Python :: 3.10
Classifier: Programming Language :: Python :: 3.11
Classifier: Topic :: Security
Classifier: Topic :: Utilities
Requires-Python: >=3.7
License-File: LICENSE
Dynamic: license-file
